CHANGELOG.txt
LICENCE.txt
MANIFEST.in
README.txt
setup.py
synd/__init__.py
syndrepo.egg-info/PKG-INFO
syndrepo.egg-info/SOURCES.txt
syndrepo.egg-info/dependency_links.txt
syndrepo.egg-info/top_level.txt